pyuff/__init__.py
pyuff/pyuff.py
pyuff/tools.py
pyuff/datasets/__init__.py
pyuff/datasets/dataset_15.py
pyuff/datasets/dataset_151.py
pyuff/datasets/dataset_164.py
pyuff/datasets/dataset_18.py
pyuff/datasets/dataset_2411.py
pyuff/datasets/dataset_2412.py
pyuff/datasets/dataset_2414.py
pyuff/datasets/dataset_2420.py
pyuff/datasets/dataset_2429.py
pyuff/datasets/dataset_2467.py
pyuff/datasets/dataset_55.py
pyuff/datasets/dataset_58.py
pyuff/datasets/dataset_82.py
pyuff-2.5.1.dist-info/METADATA
pyuff-2.5.1.dist-info/WHEEL
pyuff-2.5.1.dist-info/licenses/LICENSE
pyuff-2.5.1.dist-info/RECORD
