Metadata-Version: 2.4
Name: pyuff
Version: 2.5.1
Summary: UFF (Universal File Format) read/write.
Project-URL: homepage, https://github.com/ladisk/pyuff
Project-URL: documentation, https://pyuff.readthedocs.io/en/latest/
Project-URL: source, https://github.com/ladisk/pyuff
Author-email: "Primož Čermelj, Janko Slavič" <janko.slavic@fs.uni-lj.si>
Maintainer-email: "Janko Slavič et al." <janko.slavic@fs.uni-lj.si>
License-Expression: MIT
License-File: LICENSE
Keywords: UFF,UNV,Universal File Format,read/write
Classifier: Development Status :: 5 - Production/Stable
Classifier: Intended Audience :: Developers
Classifier: License :: OSI Approved :: MIT License
Classifier: Programming Language :: Python :: 3.10
Classifier: Topic :: Scientific/Engineering
Requires-Python: >=3.10
Requires-Dist: numpy
Provides-Extra: dev
Requires-Dist: build; extra == 'dev'
Requires-Dist: pytest; extra == 'dev'
Requires-Dist: sphinx; extra == 'dev'
Requires-Dist: sphinx-copybutton; extra == 'dev'
Requires-Dist: sphinx-rtd-theme; extra == 'dev'
Requires-Dist: twine; extra == 'dev'
Requires-Dist: wheel; extra == 'dev'
